unique_pack/__init__.py
unique_pack/cli.py
devops_unique_pack-0.0.1.dist-info/METADATA
devops_unique_pack-0.0.1.dist-info/WHEEL
devops_unique_pack-0.0.1.dist-info/top_level.txt
devops_unique_pack-0.0.1.dist-info/RECORD
