Metadata-Version: 2.1
Name: devops-unique-pack
Version: 0.0.1
Summary: Unique letter detection program
Home-page: https://git.foxminded.com.ua/foxstudent101900/task_5
Author: oleh.brailko
Author-email: oleh.brailko@gmail.com
Classifier: Programming Language :: Python :: 3
Classifier: License :: OSI Approved :: MIT License
Classifier: Operating System :: OS Independent
Requires-Python: >=3.8
